LICENSE
README.md
setup.py
./lfimap/__init__.py
./lfimap/cli.py
lfimap_ng.egg-info/PKG-INFO
lfimap_ng.egg-info/SOURCES.txt
lfimap_ng.egg-info/dependency_links.txt
lfimap_ng.egg-info/entry_points.txt
lfimap_ng.egg-info/requires.txt
lfimap_ng.egg-info/top_level.txt